pyquant/__init__.py
pyquant/command_line.py
pyquant/cpeaks.c
pyquant/cpeaks.pyd
pyquant/cpeaks.pyx
pyquant/logger.py
pyquant/peaks.py
pyquant/reader.py
pyquant/utils.py
pyquant/worker.py
pyquant/static/classifier.pickle
pyquant/static/pyquant_output.html
pyquant/tests/__init__.py
pyquant/tests/config.py
pyquant/tests/fixtures.py
pyquant/tests/integration_full.py
pyquant/tests/integration_isobaric_tags.py
pyquant/tests/integration_manual.py
pyquant/tests/mixins.py
pyquant/tests/test_convenience.py
pyquant/tests/test_math.py
pyquant/tests/test_peaks.py
pyquant/tests/test_reader.py
pyquant/tests/test_targeted.py
pyquant/tests/test_utils.py
pyquant/tests/utils.py
pyquant_ms-0.2.4.data/scripts/pyQuant
pyquant_ms-0.2.4.dist-info/DESCRIPTION.rst
pyquant_ms-0.2.4.dist-info/METADATA
pyquant_ms-0.2.4.dist-info/RECORD
pyquant_ms-0.2.4.dist-info/WHEEL
pyquant_ms-0.2.4.dist-info/entry_points.txt
pyquant_ms-0.2.4.dist-info/metadata.json
pyquant_ms-0.2.4.dist-info/top_level.txt
