Metadata-Version: 2.0
Name: pyquant-ms
Version: 0.2.4
Summary: A framework for the analysis of quantitative mass spectrometry data
Home-page: http://www.github.com/chris7/pyquant
Author: Chris Mitchell <chris.mit7@gmail.com>
Author-email: UNKNOWN
License: UNKNOWN
Platform: UNKNOWN
Classifier: License :: OSI Approved :: MIT License
Classifier: Operating System :: OS Independent
Classifier: Programming Language :: Python
Requires-Dist: cython
Requires-Dist: lxml
Requires-Dist: numpy
Requires-Dist: pandas
Requires-Dist: patsy
Requires-Dist: pythomics (>=0.3.41)
Requires-Dist: scikit-learn
Requires-Dist: scipy (>=0.18.*)
Requires-Dist: simplejson
